{
    "annotations": {
      "list": [
        {
          "builtIn": 1,
          "datasource": {
            "type": "grafana",
            "uid": "-- Grafana --"
          },
          "enable": true,
          "hide": true,
          "iconColor": "rgba(0, 211, 255, 1)",
          "name": "Annotations & Alerts",
          "type": "dashboard"
        }
      ]
    },
    "editable": true,
    "fiscalYearStartMonth": 0,
    "graphTooltip": 0,
    "id": 4,
    "links": [],
    "liveNow": false,
    "panels": [
      {
        "datasource": {
          "type": "prometheus",
          "uid": "PBFA97CFB590B2093"
        },
        "fieldConfig": {
          "defaults": {
            "color": {
              "mode": "palette-classic"
            },
            "custom": {
              "axisBorderShow": false,
              "axisCenteredZero": false,
              "axisColorMode": "text",
              "axisLabel": "",
              "axisPlacement": "auto",
              "barAlignment": 0,
              "drawStyle": "line",
              "fillOpacity": 0,
              "gradientMode": "none",
              "hideFrom": {
                "legend": false,
                "tooltip": false,
                "viz": false
              },
              "insertNulls": false,
              "lineInterpolation": "linear",
              "lineWidth": 1,
              "pointSize": 5,
              "scaleDistribution": {
                "type": "linear"
              },
              "showPoints": "auto",
              "spanNulls": false,
              "stacking": {
                "group": "A",
                "mode": "none"
              },
              "thresholdsStyle": {
                "mode": "off"
              }
            },
            "mappings": [],
            "thresholds": {
              "mode": "absolute",
              "steps": [
                {
                  "color": "green",
                  "value": null
                },
                {
                  "color": "red",
                  "value": 80
                }
              ]
            }
          },
          "overrides": []
        },
        "gridPos": {
          "h": 10,
          "w": 9,
          "x": 0,
          "y": 0
        },
        "id": 1,
        "options": {
          "legend": {
            "calcs": [],
            "displayMode": "list",
            "placement": "bottom",
            "showLegend": true
          },
          "tooltip": {
            "mode": "single",
            "sort": "none"
          }
        },
        "targets": [
          {
            "datasource": {
              "type": "prometheus",
              "uid": "PBFA97CFB590B2093"
            },
            "disableTextWrap": false,
            "editorMode": "code",
            "expr": "sum by(event) (increase(xatu_server_event_ingester_decorated_events_received_total[5m]))",
            "fullMetaSearch": false,
            "includeNullMetadata": true,
            "instant": false,
            "legendFormat": "__auto",
            "range": true,
            "refId": "A",
            "useBackend": false
          }
        ],
        "title": "Events Ingested by Xatu Server",
        "type": "timeseries"
      },
      {
        "datasource": {
          "type": "prometheus",
          "uid": "PBFA97CFB590B2093"
        },
        "fieldConfig": {
          "defaults": {
            "color": {
              "mode": "palette-classic"
            },
            "custom": {
              "axisBorderShow": false,
              "axisCenteredZero": false,
              "axisColorMode": "text",
              "axisLabel": "",
              "axisPlacement": "auto",
              "barAlignment": 0,
              "drawStyle": "line",
              "fillOpacity": 0,
              "gradientMode": "none",
              "hideFrom": {
                "legend": false,
                "tooltip": false,
                "viz": false
              },
              "insertNulls": false,
              "lineInterpolation": "linear",
              "lineWidth": 1,
              "pointSize": 5,
              "scaleDistribution": {
                "type": "linear"
              },
              "showPoints": "auto",
              "spanNulls": false,
              "stacking": {
                "group": "A",
                "mode": "none"
              },
              "thresholdsStyle": {
                "mode": "off"
              }
            },
            "mappings": [],
            "thresholds": {
              "mode": "absolute",
              "steps": [
                {
                  "color": "green",
                  "value": null
                },
                {
                  "color": "red",
                  "value": 80
                }
              ]
            }
          },
          "overrides": []
        },
        "gridPos": {
          "h": 10,
          "w": 15,
          "x": 9,
          "y": 0
        },
        "id": 3,
        "options": {
          "legend": {
            "calcs": [],
            "displayMode": "list",
            "placement": "bottom",
            "showLegend": true
          },
          "tooltip": {
            "mode": "single",
            "sort": "none"
          }
        },
        "targets": [
          {
            "datasource": {
              "type": "prometheus",
              "uid": "PBFA97CFB590B2093"
            },
            "disableTextWrap": false,
            "editorMode": "builder",
            "expr": "sum by(component_id, component_kind, component_type) (increase(vector_component_received_events_total{component_type!~\"internal_metrics|log_to_metric|prometheus_exporter\"}[5m]))",
            "fullMetaSearch": false,
            "includeNullMetadata": true,
            "instant": false,
            "legendFormat": "__auto",
            "range": true,
            "refId": "A",
            "useBackend": false
          }
        ],
        "title": "Vector Events",
        "type": "timeseries"
      },
      {
        "datasource": {
          "type": "prometheus",
          "uid": "PBFA97CFB590B2093"
        },
        "fieldConfig": {
          "defaults": {
            "color": {
              "mode": "palette-classic"
            },
            "custom": {
              "axisBorderShow": false,
              "axisCenteredZero": false,
              "axisColorMode": "text",
              "axisLabel": "",
              "axisPlacement": "auto",
              "barAlignment": 0,
              "drawStyle": "line",
              "fillOpacity": 0,
              "gradientMode": "none",
              "hideFrom": {
                "legend": false,
                "tooltip": false,
                "viz": false
              },
              "insertNulls": false,
              "lineInterpolation": "linear",
              "lineWidth": 1,
              "pointSize": 5,
              "scaleDistribution": {
                "type": "linear"
              },
              "showPoints": "auto",
              "spanNulls": false,
              "stacking": {
                "group": "A",
                "mode": "none"
              },
              "thresholdsStyle": {
                "mode": "off"
              }
            },
            "mappings": [],
            "thresholds": {
              "mode": "absolute",
              "steps": [
                {
                  "color": "green",
                  "value": null
                },
                {
                  "color": "red",
                  "value": 80
                }
              ]
            }
          },
          "overrides": []
        },
        "gridPos": {
          "h": 10,
          "w": 7,
          "x": 0,
          "y": 10
        },
        "id": 2,
        "options": {
          "legend": {
            "calcs": [],
            "displayMode": "list",
            "placement": "bottom",
            "showLegend": true
          },
          "tooltip": {
            "mode": "single",
            "sort": "none"
          }
        },
        "targets": [
          {
            "datasource": {
              "type": "prometheus",
              "uid": "PBFA97CFB590B2093"
            },
            "disableTextWrap": false,
            "editorMode": "code",
            "expr": "increase(vector_component_errors_total[5m])",
            "fullMetaSearch": false,
            "includeNullMetadata": true,
            "instant": false,
            "legendFormat": "__auto",
            "range": true,
            "refId": "A",
            "useBackend": false
          }
        ],
        "title": "Vector Errors",
        "type": "timeseries"
      }
    ],
    "refresh": "",
    "schemaVersion": 39,
    "tags": [],
    "templating": {
      "list": []
    },
    "time": {
      "from": "now-30m",
      "to": "now"
    },
    "timepicker": {},
    "timezone": "",
    "title": "Basic Overview",
    "uid": "e1aea0f4-d6ff-4fb1-91a4-e18e4e31e42a",
    "version": 2,
    "weekStart": ""
  }